pysignalr/__init__.py
pysignalr/client.py
pysignalr/exceptions.py
pysignalr/messages.py
pysignalr/protocol/__init__.py
pysignalr/protocol/abstract.py
pysignalr/protocol/json.py
pysignalr/protocol/messagepack.py
pysignalr/py.typed
pysignalr/transport/__init__.py
pysignalr/transport/abstract.py
pysignalr/transport/websocket.py
pysignalr/utils.py
pysignalr-1.2.0.dist-info/LICENSE
pysignalr-1.2.0.dist-info/METADATA
pysignalr-1.2.0.dist-info/WHEEL
pysignalr-1.2.0.dist-info/RECORD
