Metadata-Version: 2.3
Name: pysignalr
Version: 1.2.0
Summary: Modern, reliable and async-ready client for SignalR protocol
Keywords: signalr,asp,client,asyncio,json,messagepack,websockets
Author: Lev Gorodetskii
Author-email: pysignalr@drsr.io
Maintainer: Lev Gorodetskii
Maintainer-email: pysignalr@drsr.io
Requires-Python: >=3.9,<4
Classifier: Development Status :: 5 - Production/Stable
Classifier: Environment :: Console
Classifier: Intended Audience :: Developers
Classifier: License :: OSI Approved :: MIT License
Classifier: Operating System :: OS Independent
Classifier: Programming Language :: Python :: 3
Classifier: Programming Language :: Python :: 3.9
Classifier: Programming Language :: Python :: 3.10
Classifier: Programming Language :: Python :: 3.11
Classifier: Programming Language :: Python :: 3.12
Classifier: Programming Language :: Python :: 3.13
Classifier: Programming Language :: Python :: Implementation :: CPython
Classifier: Topic :: Software Development :: Libraries :: Application Frameworks
Classifier: Typing :: Typed
Requires-Dist: aiohttp
Requires-Dist: msgpack
Requires-Dist: orjson
Requires-Dist: websockets (>=12.0,<14)
Project-URL: Homepage, https://github.com/baking-bad/pysignalr
Project-URL: Repository, https://github.com/baking-bad/pysignalr
